{
	"name": "Before After",
	"title": "Before After",
	"description": "",
	"style": ["file:../../../dist/css/blocks/before-after/scss/block-before-after.css"],
	"script": "block-before-after",
	"category": "hm-sections",
	"icon": "groups",
	"apiVersion": 2,
	"keywords": [],
	"acf": {
		"mode": "preview",
		"renderTemplate": "template.php"
	},
	"styles": [],
	"supports": {
		"align": false,
		"anchor": false,
		"alignContent": false,
		"color": {
			"text": false,
			"background": false,
			"link": false
		},
		"alignText": false,
		"fullHeight": false
	},
	"attributes": {
		"mode": {
			"type": "string"
		},
		"data": {
			"type": "object"
		}
	},
	"example": {
		"attributes": {
			"mode": "preview",
			"data": {
				"block_preview_images": "block-before-after.png"
			}
		}
	}
}
